[
  {
    "type": "syntax-error",
    "module": "61a5c58e04aa5a332bbbb64927250eba_0.java",
    "obj": "",
    "line": null,
    "column": null,
    "path": "61a5c58e04aa5a332bbbb64927250eba_0.java",
    "symbol": "syntax-error",
    "message": "files/java/codes/good/MyHashMap.java:156: error: unclosed character literal\n        System.out.println(\"Contains key 'Two': \" + map.containsKey('Two')); // Contains key 'Two': true\n                                                                    ^",
    "message-id": ""
  },
  {
    "type": "syntax-error",
    "module": "61a5c58e04aa5a332bbbb64927250eba_0.java",
    "obj": "",
    "line": null,
    "column": null,
    "path": "61a5c58e04aa5a332bbbb64927250eba_0.java",
    "symbol": "syntax-error",
    "message": "files/java/codes/good/MyHashMap.java:156: error: unclosed character literal\n        System.out.println(\"Contains key 'Two': \" + map.containsKey('Two')); // Contains key 'Two': true\n                                                                        ^",
    "message-id": ""
  },
  {
    "type": "syntax-error",
    "module": "61a5c58e04aa5a332bbbb64927250eba_0.java",
    "obj": "",
    "line": null,
    "column": null,
    "path": "61a5c58e04aa5a332bbbb64927250eba_0.java",
    "symbol": "syntax-error",
    "message": "files/java/codes/good/MyHashMap.java:156: error: not a statement\n        System.out.println(\"Contains key 'Two': \" + map.containsKey('Two')); // Contains key 'Two': true\n                                                                      ^",
    "message-id": ""
  },
  {
    "type": "syntax-error",
    "module": "fea04a63e78a63868dec9e6a8a472f3d_0.java",
    "obj": "",
    "line": null,
    "column": null,
    "path": "fea04a63e78a63868dec9e6a8a472f3d_0.java",
    "symbol": "syntax-error",
    "message": "files/java/codes/good/DecimalToByteConverter.java:1: error: class, interface, or enum expected\nusing System;\n^",
    "message-id": ""
  },
  {
    "type": "syntax-error",
    "module": "fea04a63e78a63868dec9e6a8a472f3d_0.java",
    "obj": "",
    "line": null,
    "column": null,
    "path": "fea04a63e78a63868dec9e6a8a472f3d_0.java",
    "symbol": "syntax-error",
    "message": "files/java/codes/good/DecimalToByteConverter.java:20: error: ';' expected\n            decimal decimalNumber = 123.0m;\n                                         ^",
    "message-id": ""
  },
  {
    "type": "syntax-error",
    "module": "fea04a63e78a63868dec9e6a8a472f3d_0.java",
    "obj": "",
    "line": null,
    "column": null,
    "path": "fea04a63e78a63868dec9e6a8a472f3d_0.java",
    "symbol": "syntax-error",
    "message": "files/java/codes/good/DecimalToByteConverter.java:22: error: ')' expected\n            Console.WriteLine($\"Decimal {decimalNumber} converted to byte is {byteNumber}\");\n                               ^",
    "message-id": ""
  },
  {
    "type": "syntax-error",
    "module": "f07b7f53968c10c5d74c2017efa27102_1.java",
    "obj": "",
    "line": null,
    "column": null,
    "path": "f07b7f53968c10c5d74c2017efa27102_1.java",
    "symbol": "syntax-error",
    "message": "files/java/codes/good/CardShuffle.java:1: error: class, interface, or enum expected\njava\n^",
    "message-id": ""
  },
  {
    "type": "syntax-error",
    "module": "679401f148228e384da230665bcee709_5.java",
    "obj": "",
    "line": null,
    "column": null,
    "path": "679401f148228e384da230665bcee709_5.java",
    "symbol": "syntax-error",
    "message": "files/java/codes/good/KeyboardSimulator.java:1: error: class, interface, or enum expected\nusing System;\n^",
    "message-id": ""
  },
  {
    "type": "syntax-error",
    "module": "679401f148228e384da230665bcee709_5.java",
    "obj": "",
    "line": null,
    "column": null,
    "path": "679401f148228e384da230665bcee709_5.java",
    "symbol": "syntax-error",
    "message": "files/java/codes/good/KeyboardSimulator.java:2: error: class, interface, or enum expected\nusing System.Runtime.InteropServices;\n^",
    "message-id": ""
  },
  {
    "type": "syntax-error",
    "module": "679401f148228e384da230665bcee709_5.java",
    "obj": "",
    "line": null,
    "column": null,
    "path": "679401f148228e384da230665bcee709_5.java",
    "symbol": "syntax-error",
    "message": "files/java/codes/good/KeyboardSimulator.java:6: error: illegal start of type\n    private const int WM_KEYDOWN = 0x0100;\n            ^",
    "message-id": ""
  },
  {
    "type": "syntax-error",
    "module": "679401f148228e384da230665bcee709_5.java",
    "obj": "",
    "line": null,
    "column": null,
    "path": "679401f148228e384da230665bcee709_5.java",
    "symbol": "syntax-error",
    "message": "files/java/codes/good/KeyboardSimulator.java:7: error: illegal start of type\n    private const int WM_KEYUP = 0x0101;\n            ^",
    "message-id": ""
  },
  {
    "type": "syntax-error",
    "module": "679401f148228e384da230665bcee709_5.java",
    "obj": "",
    "line": null,
    "column": null,
    "path": "679401f148228e384da230665bcee709_5.java",
    "symbol": "syntax-error",
    "message": "files/java/codes/good/KeyboardSimulator.java:8: error: illegal start of type\n    private const int VK_P = 0x50;\n            ^",
    "message-id": ""
  },
  {
    "type": "syntax-error",
    "module": "679401f148228e384da230665bcee709_5.java",
    "obj": "",
    "line": null,
    "column": null,
    "path": "679401f148228e384da230665bcee709_5.java",
    "symbol": "syntax-error",
    "message": "files/java/codes/good/KeyboardSimulator.java:10: error: illegal start of type\n    [DllImport(\"user32.dll\", SetLastError = true)]\n    ^",
    "message-id": ""
  },
  {
    "type": "syntax-error",
    "module": "679401f148228e384da230665bcee709_5.java",
    "obj": "",
    "line": null,
    "column": null,
    "path": "679401f148228e384da230665bcee709_5.java",
    "symbol": "syntax-error",
    "message": "files/java/codes/good/KeyboardSimulator.java:10: error: ']' expected\n    [DllImport(\"user32.dll\", SetLastError = true)]\n     ^",
    "message-id": ""
  },
  {
    "type": "syntax-error",
    "module": "679401f148228e384da230665bcee709_5.java",
    "obj": "",
    "line": null,
    "column": null,
    "path": "679401f148228e384da230665bcee709_5.java",
    "symbol": "syntax-error",
    "message": "files/java/codes/good/KeyboardSimulator.java:10: error: illegal start of type\n    [DllImport(\"user32.dll\", SetLastError = true)]\n               ^",
    "message-id": ""
  },
  {
    "type": "syntax-error",
    "module": "679401f148228e384da230665bcee709_5.java",
    "obj": "",
    "line": null,
    "column": null,
    "path": "679401f148228e384da230665bcee709_5.java",
    "symbol": "syntax-error",
    "message": "files/java/codes/good/KeyboardSimulator.java:11: error: ';' expected\n    private static extern bool PostMessage(IntPtr hWnd, uint Msg, IntPtr wParam, IntPtr lParam);\n                              ^",
    "message-id": ""
  },
  {
    "type": "syntax-error",
    "module": "679401f148228e384da230665bcee709_5.java",
    "obj": "",
    "line": null,
    "column": null,
    "path": "679401f148228e384da230665bcee709_5.java",
    "symbol": "syntax-error",
    "message": "files/java/codes/good/KeyboardSimulator.java:11: error: invalid method declaration; return type required\n    private static extern bool PostMessage(IntPtr hWnd, uint Msg, IntPtr wParam, IntPtr lParam);\n                               ^",
    "message-id": ""
  },
  {
    "type": "syntax-error",
    "module": "679401f148228e384da230665bcee709_5.java",
    "obj": "",
    "line": null,
    "column": null,
    "path": "679401f148228e384da230665bcee709_5.java",
    "symbol": "syntax-error",
    "message": "files/java/codes/good/KeyboardSimulator.java:13: error: illegal start of type\n    [DllImport(\"user32.dll\", SetLastError = true)]\n    ^",
    "message-id": ""
  },
  {
    "type": "syntax-error",
    "module": "679401f148228e384da230665bcee709_5.java",
    "obj": "",
    "line": null,
    "column": null,
    "path": "679401f148228e384da230665bcee709_5.java",
    "symbol": "syntax-error",
    "message": "files/java/codes/good/KeyboardSimulator.java:13: error: ']' expected\n    [DllImport(\"user32.dll\", SetLastError = true)]\n     ^",
    "message-id": ""
  },
  {
    "type": "syntax-error",
    "module": "679401f148228e384da230665bcee709_5.java",
    "obj": "",
    "line": null,
    "column": null,
    "path": "679401f148228e384da230665bcee709_5.java",
    "symbol": "syntax-error",
    "message": "files/java/codes/good/KeyboardSimulator.java:13: error: illegal start of type\n    [DllImport(\"user32.dll\", SetLastError = true)]\n               ^",
    "message-id": ""
  },
  {
    "type": "syntax-error",
    "module": "679401f148228e384da230665bcee709_5.java",
    "obj": "",
    "line": null,
    "column": null,
    "path": "679401f148228e384da230665bcee709_5.java",
    "symbol": "syntax-error",
    "message": "files/java/codes/good/KeyboardSimulator.java:14: error: ';' expected\n    private static extern IntPtr FindWindow(string lpClassName, string lpWindowName);\n                                ^",
    "message-id": ""
  },
  {
    "type": "syntax-error",
    "module": "679401f148228e384da230665bcee709_5.java",
    "obj": "",
    "line": null,
    "column": null,
    "path": "679401f148228e384da230665bcee709_5.java",
    "symbol": "syntax-error",
    "message": "files/java/codes/good/KeyboardSimulator.java:14: error: invalid method declaration; return type required\n    private static extern IntPtr FindWindow(string lpClassName, string lpWindowName);\n                                 ^",
    "message-id": ""
  },
  {
    "type": "syntax-error",
    "module": "419e01e1280198cac78446178eece82a_0.java",
    "obj": "",
    "line": null,
    "column": null,
    "path": "419e01e1280198cac78446178eece82a_0.java",
    "symbol": "syntax-error",
    "message": "files/java/codes/good/ClosestNumbers.java:1: error: class, interface, or enum expected\nusing System;\n^",
    "message-id": ""
  },
  {
    "type": "syntax-error",
    "module": "419e01e1280198cac78446178eece82a_0.java",
    "obj": "",
    "line": null,
    "column": null,
    "path": "419e01e1280198cac78446178eece82a_0.java",
    "symbol": "syntax-error",
    "message": "files/java/codes/good/ClosestNumbers.java:2: error: class, interface, or enum expected\nusing System.Collections.Generic;\n^",
    "message-id": ""
  },
  {
    "type": "syntax-error",
    "module": "419e01e1280198cac78446178eece82a_0.java",
    "obj": "",
    "line": null,
    "column": null,
    "path": "419e01e1280198cac78446178eece82a_0.java",
    "symbol": "syntax-error",
    "message": "files/java/codes/good/ClosestNumbers.java:20: error: '.class' expected\n        foreach (int num in list)\n                     ^",
    "message-id": ""
  },
  {
    "type": "syntax-error",
    "module": "419e01e1280198cac78446178eece82a_0.java",
    "obj": "",
    "line": null,
    "column": null,
    "path": "419e01e1280198cac78446178eece82a_0.java",
    "symbol": "syntax-error",
    "message": "files/java/codes/good/ClosestNumbers.java:20: error: ';' expected\n        foreach (int num in list)\n                           ^",
    "message-id": ""
  },
  {
    "type": "syntax-error",
    "module": "419e01e1280198cac78446178eece82a_0.java",
    "obj": "",
    "line": null,
    "column": null,
    "path": "419e01e1280198cac78446178eece82a_0.java",
    "symbol": "syntax-error",
    "message": "files/java/codes/good/ClosestNumbers.java:20: error: not a statement\n        foreach (int num in list)\n                            ^",
    "message-id": ""
  },
  {
    "type": "syntax-error",
    "module": "419e01e1280198cac78446178eece82a_0.java",
    "obj": "",
    "line": null,
    "column": null,
    "path": "419e01e1280198cac78446178eece82a_0.java",
    "symbol": "syntax-error",
    "message": "files/java/codes/good/ClosestNumbers.java:20: error: ';' expected\n        foreach (int num in list)\n                                ^",
    "message-id": ""
  },
  {
    "type": "syntax-error",
    "module": "419e01e1280198cac78446178eece82a_0.java",
    "obj": "",
    "line": null,
    "column": null,
    "path": "419e01e1280198cac78446178eece82a_0.java",
    "symbol": "syntax-error",
    "message": "files/java/codes/good/ClosestNumbers.java:63: error: '.class' expected\n            foreach (int num in leftResults)\n                         ^",
    "message-id": ""
  },
  {
    "type": "syntax-error",
    "module": "419e01e1280198cac78446178eece82a_0.java",
    "obj": "",
    "line": null,
    "column": null,
    "path": "419e01e1280198cac78446178eece82a_0.java",
    "symbol": "syntax-error",
    "message": "files/java/codes/good/ClosestNumbers.java:63: error: ';' expected\n            foreach (int num in leftResults)\n                               ^",
    "message-id": ""
  },
  {
    "type": "syntax-error",
    "module": "419e01e1280198cac78446178eece82a_0.java",
    "obj": "",
    "line": null,
    "column": null,
    "path": "419e01e1280198cac78446178eece82a_0.java",
    "symbol": "syntax-error",
    "message": "files/java/codes/good/ClosestNumbers.java:63: error: not a statement\n            foreach (int num in leftResults)\n                                ^",
    "message-id": ""
  },
  {
    "type": "syntax-error",
    "module": "419e01e1280198cac78446178eece82a_0.java",
    "obj": "",
    "line": null,
    "column": null,
    "path": "419e01e1280198cac78446178eece82a_0.java",
    "symbol": "syntax-error",
    "message": "files/java/codes/good/ClosestNumbers.java:63: error: ';' expected\n            foreach (int num in leftResults)\n                                           ^",
    "message-id": ""
  },
  {
    "type": "syntax-error",
    "module": "419e01e1280198cac78446178eece82a_0.java",
    "obj": "",
    "line": null,
    "column": null,
    "path": "419e01e1280198cac78446178eece82a_0.java",
    "symbol": "syntax-error",
    "message": "files/java/codes/good/ClosestNumbers.java:76: error: '.class' expected\n            foreach (int num in rightResults)\n                         ^",
    "message-id": ""
  },
  {
    "type": "syntax-error",
    "module": "419e01e1280198cac78446178eece82a_0.java",
    "obj": "",
    "line": null,
    "column": null,
    "path": "419e01e1280198cac78446178eece82a_0.java",
    "symbol": "syntax-error",
    "message": "files/java/codes/good/ClosestNumbers.java:76: error: ';' expected\n            foreach (int num in rightResults)\n                               ^",
    "message-id": ""
  },
  {
    "type": "syntax-error",
    "module": "419e01e1280198cac78446178eece82a_0.java",
    "obj": "",
    "line": null,
    "column": null,
    "path": "419e01e1280198cac78446178eece82a_0.java",
    "symbol": "syntax-error",
    "message": "files/java/codes/good/ClosestNumbers.java:76: error: not a statement\n            foreach (int num in rightResults)\n                                ^",
    "message-id": ""
  },
  {
    "type": "syntax-error",
    "module": "419e01e1280198cac78446178eece82a_0.java",
    "obj": "",
    "line": null,
    "column": null,
    "path": "419e01e1280198cac78446178eece82a_0.java",
    "symbol": "syntax-error",
    "message": "files/java/codes/good/ClosestNumbers.java:76: error: ';' expected\n            foreach (int num in rightResults)\n                                            ^",
    "message-id": ""
  },
  {
    "type": "syntax-error",
    "module": "419e01e1280198cac78446178eece82a_0.java",
    "obj": "",
    "line": null,
    "column": null,
    "path": "419e01e1280198cac78446178eece82a_0.java",
    "symbol": "syntax-error",
    "message": "files/java/codes/good/ClosestNumbers.java:99: error: '.class' expected\n        foreach (int num in closestNumbers)\n                     ^",
    "message-id": ""
  },
  {
    "type": "syntax-error",
    "module": "419e01e1280198cac78446178eece82a_0.java",
    "obj": "",
    "line": null,
    "column": null,
    "path": "419e01e1280198cac78446178eece82a_0.java",
    "symbol": "syntax-error",
    "message": "files/java/codes/good/ClosestNumbers.java:99: error: ';' expected\n        foreach (int num in closestNumbers)\n                           ^",
    "message-id": ""
  },
  {
    "type": "syntax-error",
    "module": "419e01e1280198cac78446178eece82a_0.java",
    "obj": "",
    "line": null,
    "column": null,
    "path": "419e01e1280198cac78446178eece82a_0.java",
    "symbol": "syntax-error",
    "message": "files/java/codes/good/ClosestNumbers.java:99: error: not a statement\n        foreach (int num in closestNumbers)\n                            ^",
    "message-id": ""
  },
  {
    "type": "syntax-error",
    "module": "419e01e1280198cac78446178eece82a_0.java",
    "obj": "",
    "line": null,
    "column": null,
    "path": "419e01e1280198cac78446178eece82a_0.java",
    "symbol": "syntax-error",
    "message": "files/java/codes/good/ClosestNumbers.java:99: error: ';' expected\n        foreach (int num in closestNumbers)\n                                          ^",
    "message-id": ""
  },
  {
    "type": "syntax-error",
    "module": "54f9d38e06b494d65008988648338d40_2.java",
    "obj": "",
    "line": null,
    "column": null,
    "path": "54f9d38e06b494d65008988648338d40_2.java",
    "symbol": "syntax-error",
    "message": "files/java/codes/good/TextCommunication.java:1: error: class, interface, or enum expected\nusing System;\n^",
    "message-id": ""
  },
  {
    "type": "syntax-error",
    "module": "54f9d38e06b494d65008988648338d40_2.java",
    "obj": "",
    "line": null,
    "column": null,
    "path": "54f9d38e06b494d65008988648338d40_2.java",
    "symbol": "syntax-error",
    "message": "files/java/codes/good/TextCommunication.java:2: error: class, interface, or enum expected\nusing System.Diagnostics;\n^",
    "message-id": ""
  },
  {
    "type": "syntax-error",
    "module": "7ff2af27edb13a6119faa363a3b0ed80_1.java",
    "obj": "",
    "line": null,
    "column": null,
    "path": "7ff2af27edb13a6119faa363a3b0ed80_1.java",
    "symbol": "syntax-error",
    "message": "files/java/codes/good/RedisClusterSlotInfo.java:17: error: illegal start of expression\n        );\n        ^",
    "message-id": ""
  },
  {
    "type": "syntax-error",
    "module": "710bab963c282f4d82f53588e741d33f_0.java",
    "obj": "",
    "line": null,
    "column": null,
    "path": "710bab963c282f4d82f53588e741d33f_0.java",
    "symbol": "syntax-error",
    "message": "files/java/codes/good/CostAwareKMeans.java:1: error: class, interface, or enum expected\nusing Accord.MachineLearning;\n^",
    "message-id": ""
  },
  {
    "type": "syntax-error",
    "module": "710bab963c282f4d82f53588e741d33f_0.java",
    "obj": "",
    "line": null,
    "column": null,
    "path": "710bab963c282f4d82f53588e741d33f_0.java",
    "symbol": "syntax-error",
    "message": "files/java/codes/good/CostAwareKMeans.java:2: error: class, interface, or enum expected\nusing Accord.MachineLearning.VectorMachines;\n^",
    "message-id": ""
  },
  {
    "type": "syntax-error",
    "module": "710bab963c282f4d82f53588e741d33f_0.java",
    "obj": "",
    "line": null,
    "column": null,
    "path": "710bab963c282f4d82f53588e741d33f_0.java",
    "symbol": "syntax-error",
    "message": "files/java/codes/good/CostAwareKMeans.java:3: error: class, interface, or enum expected\nusing Accord.MachineLearning.VectorMachines.Learning;\n^",
    "message-id": ""
  },
  {
    "type": "syntax-error",
    "module": "710bab963c282f4d82f53588e741d33f_0.java",
    "obj": "",
    "line": null,
    "column": null,
    "path": "710bab963c282f4d82f53588e741d33f_0.java",
    "symbol": "syntax-error",
    "message": "files/java/codes/good/CostAwareKMeans.java:4: error: class, interface, or enum expected\nusing Accord.MachineLearning.VectorMachines.SupportVectorMachines;\n^",
    "message-id": ""
  },
  {
    "type": "syntax-error",
    "module": "710bab963c282f4d82f53588e741d33f_0.java",
    "obj": "",
    "line": null,
    "column": null,
    "path": "710bab963c282f4d82f53588e741d33f_0.java",
    "symbol": "syntax-error",
    "message": "files/java/codes/good/CostAwareKMeans.java:5: error: class, interface, or enum expected\nusing Accord.MachineLearning.VectorMachines.SupportVectorMachines.Kernels;\n^",
    "message-id": ""
  },
  {
    "type": "syntax-error",
    "module": "710bab963c282f4d82f53588e741d33f_0.java",
    "obj": "",
    "line": null,
    "column": null,
    "path": "710bab963c282f4d82f53588e741d33f_0.java",
    "symbol": "syntax-error",
    "message": "files/java/codes/good/CostAwareKMeans.java:6: error: class, interface, or enum expected\nusing Accord.Math;\n^",
    "message-id": ""
  },
  {
    "type": "syntax-error",
    "module": "710bab963c282f4d82f53588e741d33f_0.java",
    "obj": "",
    "line": null,
    "column": null,
    "path": "710bab963c282f4d82f53588e741d33f_0.java",
    "symbol": "syntax-error",
    "message": "files/java/codes/good/CostAwareKMeans.java:7: error: class, interface, or enum expected\nusing Accord.Statistics.Kernels;\n^",
    "message-id": ""
  },
  {
    "type": "syntax-error",
    "module": "710bab963c282f4d82f53588e741d33f_0.java",
    "obj": "",
    "line": null,
    "column": null,
    "path": "710bab963c282f4d82f53588e741d33f_0.java",
    "symbol": "syntax-error",
    "message": "files/java/codes/good/CostAwareKMeans.java:8: error: class, interface, or enum expected\nusing System;\n^",
    "message-id": ""
  },
  {
    "type": "syntax-error",
    "module": "710bab963c282f4d82f53588e741d33f_0.java",
    "obj": "",
    "line": null,
    "column": null,
    "path": "710bab963c282f4d82f53588e741d33f_0.java",
    "symbol": "syntax-error",
    "message": "files/java/codes/good/CostAwareKMeans.java:10: error: class, interface, or enum expected\nnamespace GPSKMeans\n^",
    "message-id": ""
  },
  {
    "type": "syntax-error",
    "module": "710bab963c282f4d82f53588e741d33f_0.java",
    "obj": "",
    "line": null,
    "column": null,
    "path": "710bab963c282f4d82f53588e741d33f_0.java",
    "symbol": "syntax-error",
    "message": "files/java/codes/good/CostAwareKMeans.java:13: error: '{' expected\n    public class CostAwareKMeans : KMeans\n                                ^",
    "message-id": ""
  },
  {
    "type": "syntax-error",
    "module": "710bab963c282f4d82f53588e741d33f_0.java",
    "obj": "",
    "line": null,
    "column": null,
    "path": "710bab963c282f4d82f53588e741d33f_0.java",
    "symbol": "syntax-error",
    "message": "files/java/codes/good/CostAwareKMeans.java:16: error: ']' expected\n        private double[,] costMatrix;\n                       ^",
    "message-id": ""
  },
  {
    "type": "syntax-error",
    "module": "710bab963c282f4d82f53588e741d33f_0.java",
    "obj": "",
    "line": null,
    "column": null,
    "path": "710bab963c282f4d82f53588e741d33f_0.java",
    "symbol": "syntax-error",
    "message": "files/java/codes/good/CostAwareKMeans.java:16: error: <identifier> expected\n        private double[,] costMatrix;\n                        ^",
    "message-id": ""
  },
  {
    "type": "syntax-error",
    "module": "710bab963c282f4d82f53588e741d33f_0.java",
    "obj": "",
    "line": null,
    "column": null,
    "path": "710bab963c282f4d82f53588e741d33f_0.java",
    "symbol": "syntax-error",
    "message": "files/java/codes/good/CostAwareKMeans.java:16: error: <identifier> expected\n        private double[,] costMatrix;\n                                    ^",
    "message-id": ""
  },
  {
    "type": "syntax-error",
    "module": "710bab963c282f4d82f53588e741d33f_0.java",
    "obj": "",
    "line": null,
    "column": null,
    "path": "710bab963c282f4d82f53588e741d33f_0.java",
    "symbol": "syntax-error",
    "message": "files/java/codes/good/CostAwareKMeans.java:25: error: ']' expected\n        public CostAwareKMeans(int clusters, double[,] costMatrix, double[] nodeWeights, double maxClusterWeight) \n                                                    ^",
    "message-id": ""
  },
  {
    "type": "syntax-error",
    "module": "710bab963c282f4d82f53588e741d33f_0.java",
    "obj": "",
    "line": null,
    "column": null,
    "path": "710bab963c282f4d82f53588e741d33f_0.java",
    "symbol": "syntax-error",
    "message": "files/java/codes/good/CostAwareKMeans.java:25: error: illegal start of type\n        public CostAwareKMeans(int clusters, double[,] costMatrix, double[] nodeWeights, double maxClusterWeight) \n                                                     ^",
    "message-id": ""
  },
  {
    "type": "syntax-error",
    "module": "710bab963c282f4d82f53588e741d33f_0.java",
    "obj": "",
    "line": null,
    "column": null,
    "path": "710bab963c282f4d82f53588e741d33f_0.java",
    "symbol": "syntax-error",
    "message": "files/java/codes/good/CostAwareKMeans.java:25: error: <identifier> expected\n        public CostAwareKMeans(int clusters, double[,] costMatrix, double[] nodeWeights, double maxClusterWeight) \n                                                                                        ^",
    "message-id": ""
  },
  {
    "type": "syntax-error",
    "module": "710bab963c282f4d82f53588e741d33f_0.java",
    "obj": "",
    "line": null,
    "column": null,
    "path": "710bab963c282f4d82f53588e741d33f_0.java",
    "symbol": "syntax-error",
    "message": "files/java/codes/good/CostAwareKMeans.java:25: error: ';' expected\n        public CostAwareKMeans(int clusters, double[,] costMatrix, double[] nodeWeights, double maxClusterWeight) \n                                                                                                                ^",
    "message-id": ""
  },
  {
    "type": "syntax-error",
    "module": "710bab963c282f4d82f53588e741d33f_0.java",
    "obj": "",
    "line": null,
    "column": null,
    "path": "710bab963c282f4d82f53588e741d33f_0.java",
    "symbol": "syntax-error",
    "message": "files/java/codes/good/CostAwareKMeans.java:26: error: invalid method declaration; return type required\n            : base(clusters)\n              ^",
    "message-id": ""
  },
  {
    "type": "syntax-error",
    "module": "710bab963c282f4d82f53588e741d33f_0.java",
    "obj": "",
    "line": null,
    "column": null,
    "path": "710bab963c282f4d82f53588e741d33f_0.java",
    "symbol": "syntax-error",
    "message": "files/java/codes/good/CostAwareKMeans.java:26: error: <identifier> expected\n            : base(clusters)\n                           ^",
    "message-id": ""
  },
  {
    "type": "syntax-error",
    "module": "710bab963c282f4d82f53588e741d33f_0.java",
    "obj": "",
    "line": null,
    "column": null,
    "path": "710bab963c282f4d82f53588e741d33f_0.java",
    "symbol": "syntax-error",
    "message": "files/java/codes/good/CostAwareKMeans.java:34: error: <identifier> expected\n        protected override void UpdateMeans(int[] clustering)\n                          ^",
    "message-id": ""
  },
  {
    "type": "syntax-error",
    "module": "710bab963c282f4d82f53588e741d33f_0.java",
    "obj": "",
    "line": null,
    "column": null,
    "path": "710bab963c282f4d82f53588e741d33f_0.java",
    "symbol": "syntax-error",
    "message": "files/java/codes/good/CostAwareKMeans.java:90: error: ']' expected\n                    currentCost += costMatrix[point, i];\n                                                   ^",
    "message-id": ""
  },
  {
    "type": "syntax-error",
    "module": "710bab963c282f4d82f53588e741d33f_0.java",
    "obj": "",
    "line": null,
    "column": null,
    "path": "710bab963c282f4d82f53588e741d33f_0.java",
    "symbol": "syntax-error",
    "message": "files/java/codes/good/CostAwareKMeans.java:90: error: not a statement\n                    currentCost += costMatrix[point, i];\n                                                     ^",
    "message-id": ""
  },
  {
    "type": "syntax-error",
    "module": "710bab963c282f4d82f53588e741d33f_0.java",
    "obj": "",
    "line": null,
    "column": null,
    "path": "710bab963c282f4d82f53588e741d33f_0.java",
    "symbol": "syntax-error",
    "message": "files/java/codes/good/CostAwareKMeans.java:90: error: ';' expected\n                    currentCost += costMatrix[point, i];\n                                                      ^",
    "message-id": ""
  },
  {
    "type": "syntax-error",
    "module": "710bab963c282f4d82f53588e741d33f_0.java",
    "obj": "",
    "line": null,
    "column": null,
    "path": "710bab963c282f4d82f53588e741d33f_0.java",
    "symbol": "syntax-error",
    "message": "files/java/codes/good/CostAwareKMeans.java:94: error: ']' expected\n                    newCost += costMatrix[point, i];\n                                               ^",
    "message-id": ""
  },
  {
    "type": "syntax-error",
    "module": "710bab963c282f4d82f53588e741d33f_0.java",
    "obj": "",
    "line": null,
    "column": null,
    "path": "710bab963c282f4d82f53588e741d33f_0.java",
    "symbol": "syntax-error",
    "message": "files/java/codes/good/CostAwareKMeans.java:94: error: not a statement\n                    newCost += costMatrix[point, i];\n                                                 ^",
    "message-id": ""
  },
  {
    "type": "syntax-error",
    "module": "710bab963c282f4d82f53588e741d33f_0.java",
    "obj": "",
    "line": null,
    "column": null,
    "path": "710bab963c282f4d82f53588e741d33f_0.java",
    "symbol": "syntax-error",
    "message": "files/java/codes/good/CostAwareKMeans.java:94: error: ';' expected\n                    newCost += costMatrix[point, i];\n                                                  ^",
    "message-id": ""
  },
  {
    "type": "syntax-error",
    "module": "710bab963c282f4d82f53588e741d33f_0.java",
    "obj": "",
    "line": null,
    "column": null,
    "path": "710bab963c282f4d82f53588e741d33f_0.java",
    "symbol": "syntax-error",
    "message": "files/java/codes/good/CostAwareKMeans.java:109: error: ']' expected\n            double[,] gpsCoordinates = new double[,]\n                   ^",
    "message-id": ""
  },
  {
    "type": "syntax-error",
    "module": "710bab963c282f4d82f53588e741d33f_0.java",
    "obj": "",
    "line": null,
    "column": null,
    "path": "710bab963c282f4d82f53588e741d33f_0.java",
    "symbol": "syntax-error",
    "message": "files/java/codes/good/CostAwareKMeans.java:109: error: not a statement\n            double[,] gpsCoordinates = new double[,]\n                  ^",
    "message-id": ""
  },
  {
    "type": "syntax-error",
    "module": "710bab963c282f4d82f53588e741d33f_0.java",
    "obj": "",
    "line": null,
    "column": null,
    "path": "710bab963c282f4d82f53588e741d33f_0.java",
    "symbol": "syntax-error",
    "message": "files/java/codes/good/CostAwareKMeans.java:109: error: illegal start of expression\n            double[,] gpsCoordinates = new double[,]\n                                                  ^",
    "message-id": ""
  },
  {
    "type": "syntax-error",
    "module": "710bab963c282f4d82f53588e741d33f_0.java",
    "obj": "",
    "line": null,
    "column": null,
    "path": "710bab963c282f4d82f53588e741d33f_0.java",
    "symbol": "syntax-error",
    "message": "files/java/codes/good/CostAwareKMeans.java:111: error: not a statement\n                { 45.65737, 25.6012 },\n                  ^",
    "message-id": ""
  },
  {
    "type": "syntax-error",
    "module": "710bab963c282f4d82f53588e741d33f_0.java",
    "obj": "",
    "line": null,
    "column": null,
    "path": "710bab963c282f4d82f53588e741d33f_0.java",
    "symbol": "syntax-error",
    "message": "files/java/codes/good/CostAwareKMeans.java:111: error: ';' expected\n                { 45.65737, 25.6012 },\n                          ^",
    "message-id": ""
  },
  {
    "type": "syntax-error",
    "module": "710bab963c282f4d82f53588e741d33f_0.java",
    "obj": "",
    "line": null,
    "column": null,
    "path": "710bab963c282f4d82f53588e741d33f_0.java",
    "symbol": "syntax-error",
    "message": "files/java/codes/good/CostAwareKMeans.java:111: error: illegal start of expression\n                { 45.65737, 25.6012 },\n                                     ^",
    "message-id": ""
  },
  {
    "type": "syntax-error",
    "module": "710bab963c282f4d82f53588e741d33f_0.java",
    "obj": "",
    "line": null,
    "column": null,
    "path": "710bab963c282f4d82f53588e741d33f_0.java",
    "symbol": "syntax-error",
    "message": "files/java/codes/good/CostAwareKMeans.java:112: error: not a statement\n                { 46.07813, 23.50622 },\n                  ^",
    "message-id": ""
  },
  {
    "type": "syntax-error",
    "module": "710bab963c282f4d82f53588e741d33f_0.java",
    "obj": "",
    "line": null,
    "column": null,
    "path": "710bab963c282f4d82f53588e741d33f_0.java",
    "symbol": "syntax-error",
    "message": "files/java/codes/good/CostAwareKMeans.java:112: error: ';' expected\n                { 46.07813, 23.50622 },\n                          ^",
    "message-id": ""
  },
  {
    "type": "syntax-error",
    "module": "710bab963c282f4d82f53588e741d33f_0.java",
    "obj": "",
    "line": null,
    "column": null,
    "path": "710bab963c282f4d82f53588e741d33f_0.java",
    "symbol": "syntax-error",
    "message": "files/java/codes/good/CostAwareKMeans.java:112: error: illegal start of expression\n                { 46.07813, 23.50622 },\n                                      ^",
    "message-id": ""
  },
  {
    "type": "syntax-error",
    "module": "710bab963c282f4d82f53588e741d33f_0.java",
    "obj": "",
    "line": null,
    "column": null,
    "path": "710bab963c282f4d82f53588e741d33f_0.java",
    "symbol": "syntax-error",
    "message": "files/java/codes/good/CostAwareKMeans.java:113: error: not a statement\n                { 44.43534, 26.09992 },\n                  ^",
    "message-id": ""
  },
  {
    "type": "syntax-error",
    "module": "710bab963c282f4d82f53588e741d33f_0.java",
    "obj": "",
    "line": null,
    "column": null,
    "path": "710bab963c282f4d82f53588e741d33f_0.java",
    "symbol": "syntax-error",
    "message": "files/java/codes/good/CostAwareKMeans.java:113: error: ';' expected\n                { 44.43534, 26.09992 },\n                          ^",
    "message-id": ""
  },
  {
    "type": "syntax-error",
    "module": "710bab963c282f4d82f53588e741d33f_0.java",
    "obj": "",
    "line": null,
    "column": null,
    "path": "710bab963c282f4d82f53588e741d33f_0.java",
    "symbol": "syntax-error",
    "message": "files/java/codes/good/CostAwareKMeans.java:113: error: illegal start of expression\n                { 44.43534, 26.09992 },\n                                      ^",
    "message-id": ""
  },
  {
    "type": "syntax-error",
    "module": "710bab963c282f4d82f53588e741d33f_0.java",
    "obj": "",
    "line": null,
    "column": null,
    "path": "710bab963c282f4d82f53588e741d33f_0.java",
    "symbol": "syntax-error",
    "message": "files/java/codes/good/CostAwareKMeans.java:118: error: ']' expected\n            double[,] costMatrix = new double[,]\n                   ^",
    "message-id": ""
  },
  {
    "type": "syntax-error",
    "module": "710bab963c282f4d82f53588e741d33f_0.java",
    "obj": "",
    "line": null,
    "column": null,
    "path": "710bab963c282f4d82f53588e741d33f_0.java",
    "symbol": "syntax-error",
    "message": "files/java/codes/good/CostAwareKMeans.java:118: error: not a statement\n            double[,] costMatrix = new double[,]\n                  ^",
    "message-id": ""
  },
  {
    "type": "syntax-error",
    "module": "710bab963c282f4d82f53588e741d33f_0.java",
    "obj": "",
    "line": null,
    "column": null,
    "path": "710bab963c282f4d82f53588e741d33f_0.java",
    "symbol": "syntax-error",
    "message": "files/java/codes/good/CostAwareKMeans.java:118: error: illegal start of expression\n            double[,] costMatrix = new double[,]\n                                              ^",
    "message-id": ""
  },
  {
    "type": "syntax-error",
    "module": "710bab963c282f4d82f53588e741d33f_0.java",
    "obj": "",
    "line": null,
    "column": null,
    "path": "710bab963c282f4d82f53588e741d33f_0.java",
    "symbol": "syntax-error",
    "message": "files/java/codes/good/CostAwareKMeans.java:120: error: not a statement\n                { 0.0, 1.0, 2.0 },\n                  ^",
    "message-id": ""
  },
  {
    "type": "syntax-error",
    "module": "710bab963c282f4d82f53588e741d33f_0.java",
    "obj": "",
    "line": null,
    "column": null,
    "path": "710bab963c282f4d82f53588e741d33f_0.java",
    "symbol": "syntax-error",
    "message": "files/java/codes/good/CostAwareKMeans.java:120: error: ';' expected\n                { 0.0, 1.0, 2.0 },\n                     ^",
    "message-id": ""
  },
  {
    "type": "syntax-error",
    "module": "710bab963c282f4d82f53588e741d33f_0.java",
    "obj": "",
    "line": null,
    "column": null,
    "path": "710bab963c282f4d82f53588e741d33f_0.java",
    "symbol": "syntax-error",
    "message": "files/java/codes/good/CostAwareKMeans.java:120: error: illegal start of expression\n                { 0.0, 1.0, 2.0 },\n                                 ^",
    "message-id": ""
  },
  {
    "type": "syntax-error",
    "module": "710bab963c282f4d82f53588e741d33f_0.java",
    "obj": "",
    "line": null,
    "column": null,
    "path": "710bab963c282f4d82f53588e741d33f_0.java",
    "symbol": "syntax-error",
    "message": "files/java/codes/good/CostAwareKMeans.java:121: error: not a statement\n                { 1.0, 0.0, 3.0 },\n                  ^",
    "message-id": ""
  },
  {
    "type": "syntax-error",
    "module": "710bab963c282f4d82f53588e741d33f_0.java",
    "obj": "",
    "line": null,
    "column": null,
    "path": "710bab963c282f4d82f53588e741d33f_0.java",
    "symbol": "syntax-error",
    "message": "files/java/codes/good/CostAwareKMeans.java:121: error: ';' expected\n                { 1.0, 0.0, 3.0 },\n                     ^",
    "message-id": ""
  },
  {
    "type": "syntax-error",
    "module": "710bab963c282f4d82f53588e741d33f_0.java",
    "obj": "",
    "line": null,
    "column": null,
    "path": "710bab963c282f4d82f53588e741d33f_0.java",
    "symbol": "syntax-error",
    "message": "files/java/codes/good/CostAwareKMeans.java:121: error: illegal start of expression\n                { 1.0, 0.0, 3.0 },\n                                 ^",
    "message-id": ""
  },
  {
    "type": "syntax-error",
    "module": "710bab963c282f4d82f53588e741d33f_0.java",
    "obj": "",
    "line": null,
    "column": null,
    "path": "710bab963c282f4d82f53588e741d33f_0.java",
    "symbol": "syntax-error",
    "message": "files/java/codes/good/CostAwareKMeans.java:122: error: not a statement\n                { 2.0, 3.0, 0.0 },\n                  ^",
    "message-id": ""
  },
  {
    "type": "syntax-error",
    "module": "710bab963c282f4d82f53588e741d33f_0.java",
    "obj": "",
    "line": null,
    "column": null,
    "path": "710bab963c282f4d82f53588e741d33f_0.java",
    "symbol": "syntax-error",
    "message": "files/java/codes/good/CostAwareKMeans.java:122: error: ';' expected\n                { 2.0, 3.0, 0.0 },\n                     ^",
    "message-id": ""
  },
  {
    "type": "syntax-error",
    "module": "710bab963c282f4d82f53588e741d33f_0.java",
    "obj": "",
    "line": null,
    "column": null,
    "path": "710bab963c282f4d82f53588e741d33f_0.java",
    "symbol": "syntax-error",
    "message": "files/java/codes/good/CostAwareKMeans.java:122: error: illegal start of expression\n                { 2.0, 3.0, 0.0 },\n                                 ^",
    "message-id": ""
  },
  {
    "type": "syntax-error",
    "module": "710bab963c282f4d82f53588e741d33f_0.java",
    "obj": "",
    "line": null,
    "column": null,
    "path": "710bab963c282f4d82f53588e741d33f_0.java",
    "symbol": "syntax-error",
    "message": "files/java/codes/good/CostAwareKMeans.java:136: error: ')' expected\n            CostAwareKMeans kmeans = new CostAwareKMeans(clusters: 3, costMatrix: costMatrix, nodeWeights: nodeWeights, maxClusterWeight: 8.0);\n                                                                 ^",
    "message-id": ""
  },
  {
    "type": "syntax-error",
    "module": "710bab963c282f4d82f53588e741d33f_0.java",
    "obj": "",
    "line": null,
    "column": null,
    "path": "710bab963c282f4d82f53588e741d33f_0.java",
    "symbol": "syntax-error",
    "message": "files/java/codes/good/CostAwareKMeans.java:136: error: not a statement\n            CostAwareKMeans kmeans = new CostAwareKMeans(clusters: 3, costMatrix: costMatrix, nodeWeights: nodeWeights, maxClusterWeight: 8.0);\n                                                                                  ^",
    "message-id": ""
  },
  {
    "type": "syntax-error",
    "module": "710bab963c282f4d82f53588e741d33f_0.java",
    "obj": "",
    "line": null,
    "column": null,
    "path": "710bab963c282f4d82f53588e741d33f_0.java",
    "symbol": "syntax-error",
    "message": "files/java/codes/good/CostAwareKMeans.java:136: error: ';' expected\n            CostAwareKMeans kmeans = new CostAwareKMeans(clusters: 3, costMatrix: costMatrix, nodeWeights: nodeWeights, maxClusterWeight: 8.0);\n                                                                                            ^",
    "message-id": ""
  },
  {
    "type": "syntax-error",
    "module": "710bab963c282f4d82f53588e741d33f_0.java",
    "obj": "",
    "line": null,
    "column": null,
    "path": "710bab963c282f4d82f53588e741d33f_0.java",
    "symbol": "syntax-error",
    "message": "files/java/codes/good/CostAwareKMeans.java:136: error: not a statement\n            CostAwareKMeans kmeans = new CostAwareKMeans(clusters: 3, costMatrix: costMatrix, nodeWeights: nodeWeights, maxClusterWeight: 8.0);\n                                                                                                           ^",
    "message-id": ""
  },
  {
    "type": "syntax-error",
    "module": "710bab963c282f4d82f53588e741d33f_0.java",
    "obj": "",
    "line": null,
    "column": null,
    "path": "710bab963c282f4d82f53588e741d33f_0.java",
    "symbol": "syntax-error",
    "message": "files/java/codes/good/CostAwareKMeans.java:136: error: ';' expected\n            CostAwareKMeans kmeans = new CostAwareKMeans(clusters: 3, costMatrix: costMatrix, nodeWeights: nodeWeights, maxClusterWeight: 8.0);\n                                                                                                                      ^",
    "message-id": ""
  },
  {
    "type": "syntax-error",
    "module": "710bab963c282f4d82f53588e741d33f_0.java",
    "obj": "",
    "line": null,
    "column": null,
    "path": "710bab963c282f4d82f53588e741d33f_0.java",
    "symbol": "syntax-error",
    "message": "files/java/codes/good/CostAwareKMeans.java:136: error: not a statement\n            CostAwareKMeans kmeans = new CostAwareKMeans(clusters: 3, costMatrix: costMatrix, nodeWeights: nodeWeights, maxClusterWeight: 8.0);\n                                                                                                                                          ^",
    "message-id": ""
  },
  {
    "type": "syntax-error",
    "module": "710bab963c282f4d82f53588e741d33f_0.java",
    "obj": "",
    "line": null,
    "column": null,
    "path": "710bab963c282f4d82f53588e741d33f_0.java",
    "symbol": "syntax-error",
    "message": "files/java/codes/good/CostAwareKMeans.java:136: error: ';' expected\n            CostAwareKMeans kmeans = new CostAwareKMeans(clusters: 3, costMatrix: costMatrix, nodeWeights: nodeWeights, maxClusterWeight: 8.0);\n                                                                                                                                             ^\n100 errors",
    "message-id": ""
  }
]