[
  {
    "type": "syntax-error",
    "module": "4ec354fdd004f1785b5058d8f5f48a08_1.java",
    "obj": "",
    "line": null,
    "column": null,
    "path": "4ec354fdd004f1785b5058d8f5f48a08_1.java",
    "symbol": "syntax-error",
    "message": "files/java/codes/good/BoardGameModel.java:17: error: illegal start of type\n    ...\n    ^",
    "message-id": ""
  },
  {
    "type": "syntax-error",
    "module": "4ec354fdd004f1785b5058d8f5f48a08_1.java",
    "obj": "",
    "line": null,
    "column": null,
    "path": "4ec354fdd004f1785b5058d8f5f48a08_1.java",
    "symbol": "syntax-error",
    "message": "files/java/codes/good/BoardGameModel.java:72: error: illegal start of type\n    ...\n    ^",
    "message-id": ""
  },
  {
    "type": "syntax-error",
    "module": "329dc346a079a66198c70b47faa08566_0.java",
    "obj": "",
    "line": null,
    "column": null,
    "path": "329dc346a079a66198c70b47faa08566_0.java",
    "symbol": "syntax-error",
    "message": "files/java/codes/good/LevelGenerator.java:1: error: class, interface, enum, or record expected\nusing UnityEngine;\n^",
    "message-id": ""
  },
  {
    "type": "syntax-error",
    "module": "329dc346a079a66198c70b47faa08566_0.java",
    "obj": "",
    "line": null,
    "column": null,
    "path": "329dc346a079a66198c70b47faa08566_0.java",
    "symbol": "syntax-error",
    "message": "files/java/codes/good/LevelGenerator.java:3: error: '{' expected\npublic class LevelGenerator : MonoBehaviour\n                           ^",
    "message-id": ""
  },
  {
    "type": "syntax-error",
    "module": "8d3731591c616b56c3841798f4303627_2.java",
    "obj": "",
    "line": null,
    "column": null,
    "path": "8d3731591c616b56c3841798f4303627_2.java",
    "symbol": "syntax-error",
    "message": "files/java/codes/good/KeyFramesExtractor.java:3: error: ';' expected\n    public event EventHandler<KeyFramesExtractorProgressEventArgs> KeyFramesExtractorProgress;\n                             ^",
    "message-id": ""
  },
  {
    "type": "syntax-error",
    "module": "8d3731591c616b56c3841798f4303627_2.java",
    "obj": "",
    "line": null,
    "column": null,
    "path": "8d3731591c616b56c3841798f4303627_2.java",
    "symbol": "syntax-error",
    "message": "files/java/codes/good/KeyFramesExtractor.java:3: error: <identifier> expected\n    public event EventHandler<KeyFramesExtractorProgressEventArgs> KeyFramesExtractorProgress;\n                                                                                             ^",
    "message-id": ""
  },
  {
    "type": "syntax-error",
    "module": "8d3731591c616b56c3841798f4303627_2.java",
    "obj": "",
    "line": null,
    "column": null,
    "path": "8d3731591c616b56c3841798f4303627_2.java",
    "symbol": "syntax-error",
    "message": "files/java/codes/good/KeyFramesExtractor.java:5: error: ';' expected\n    public List<long> Keyframes { get; private set; } = new List<long>();\n                               ^",
    "message-id": ""
  },
  {
    "type": "syntax-error",
    "module": "8d3731591c616b56c3841798f4303627_2.java",
    "obj": "",
    "line": null,
    "column": null,
    "path": "8d3731591c616b56c3841798f4303627_2.java",
    "symbol": "syntax-error",
    "message": "files/java/codes/good/KeyFramesExtractor.java:5: error: not a statement\n    public List<long> Keyframes { get; private set; } = new List<long>();\n                                  ^",
    "message-id": ""
  },
  {
    "type": "syntax-error",
    "module": "8d3731591c616b56c3841798f4303627_2.java",
    "obj": "",
    "line": null,
    "column": null,
    "path": "8d3731591c616b56c3841798f4303627_2.java",
    "symbol": "syntax-error",
    "message": "files/java/codes/good/KeyFramesExtractor.java:5: error: illegal start of expression\n    public List<long> Keyframes { get; private set; } = new List<long>();\n                                       ^",
    "message-id": ""
  },
  {
    "type": "syntax-error",
    "module": "8d3731591c616b56c3841798f4303627_2.java",
    "obj": "",
    "line": null,
    "column": null,
    "path": "8d3731591c616b56c3841798f4303627_2.java",
    "symbol": "syntax-error",
    "message": "files/java/codes/good/KeyFramesExtractor.java:5: error: <identifier> expected\n    public List<long> Keyframes { get; private set; } = new List<long>();\n                                                  ^",
    "message-id": ""
  },
  {
    "type": "syntax-error",
    "module": "8d3731591c616b56c3841798f4303627_2.java",
    "obj": "",
    "line": null,
    "column": null,
    "path": "8d3731591c616b56c3841798f4303627_2.java",
    "symbol": "syntax-error",
    "message": "files/java/codes/good/KeyFramesExtractor.java:5: error: class, interface, enum, or record expected\n    public List<long> Keyframes { get; private set; } = new List<long>();\n                                                      ^",
    "message-id": ""
  },
  {
    "type": "syntax-error",
    "module": "8d3731591c616b56c3841798f4303627_2.java",
    "obj": "",
    "line": null,
    "column": null,
    "path": "8d3731591c616b56c3841798f4303627_2.java",
    "symbol": "syntax-error",
    "message": "files/java/codes/good/KeyFramesExtractor.java:6: error: class, interface, enum, or record expected\n    public bool InProgress { get; set; } = false;\n           ^",
    "message-id": ""
  },
  {
    "type": "syntax-error",
    "module": "8d3731591c616b56c3841798f4303627_2.java",
    "obj": "",
    "line": null,
    "column": null,
    "path": "8d3731591c616b56c3841798f4303627_2.java",
    "symbol": "syntax-error",
    "message": "files/java/codes/good/KeyFramesExtractor.java:6: error: class, interface, enum, or record expected\n    public bool InProgress { get; set; } = false;\n                                  ^",
    "message-id": ""
  },
  {
    "type": "syntax-error",
    "module": "8d3731591c616b56c3841798f4303627_2.java",
    "obj": "",
    "line": null,
    "column": null,
    "path": "8d3731591c616b56c3841798f4303627_2.java",
    "symbol": "syntax-error",
    "message": "files/java/codes/good/KeyFramesExtractor.java:6: error: class, interface, enum, or record expected\n    public bool InProgress { get; set; } = false;\n                                       ^",
    "message-id": ""
  },
  {
    "type": "syntax-error",
    "module": "8d3731591c616b56c3841798f4303627_2.java",
    "obj": "",
    "line": null,
    "column": null,
    "path": "8d3731591c616b56c3841798f4303627_2.java",
    "symbol": "syntax-error",
    "message": "files/java/codes/good/KeyFramesExtractor.java:8: error: class, interface, enum, or record expected\n    private CancellationTokenSource tokenSource;\n            ^",
    "message-id": ""
  },
  {
    "type": "syntax-error",
    "module": "8d3731591c616b56c3841798f4303627_2.java",
    "obj": "",
    "line": null,
    "column": null,
    "path": "8d3731591c616b56c3841798f4303627_2.java",
    "symbol": "syntax-error",
    "message": "files/java/codes/good/KeyFramesExtractor.java:9: error: class, interface, enum, or record expected\n    private Task task;\n            ^",
    "message-id": ""
  },
  {
    "type": "syntax-error",
    "module": "cfdc9520bbdd46b1f917e24ceb609cb5_2.java",
    "obj": "",
    "line": null,
    "column": null,
    "path": "cfdc9520bbdd46b1f917e24ceb609cb5_2.java",
    "symbol": "syntax-error",
    "message": "files/java/codes/good/MyTask2.java:20: error: class, interface, enum, or record expected\nRunnable task1 = new MyTask2(\"Hello\");\n^",
    "message-id": ""
  },
  {
    "type": "syntax-error",
    "module": "cfdc9520bbdd46b1f917e24ceb609cb5_2.java",
    "obj": "",
    "line": null,
    "column": null,
    "path": "cfdc9520bbdd46b1f917e24ceb609cb5_2.java",
    "symbol": "syntax-error",
    "message": "files/java/codes/good/MyTask2.java:21: error: class, interface, enum, or record expected\nRunnable task2 = new MyTask2(\"World\");\n^",
    "message-id": ""
  },
  {
    "type": "syntax-error",
    "module": "cfdc9520bbdd46b1f917e24ceb609cb5_2.java",
    "obj": "",
    "line": null,
    "column": null,
    "path": "cfdc9520bbdd46b1f917e24ceb609cb5_2.java",
    "symbol": "syntax-error",
    "message": "files/java/codes/good/MyTask2.java:22: error: class, interface, enum, or record expected\nRunnable task3 = new MyTask2(\"From my task\");\n^",
    "message-id": ""
  },
  {
    "type": "syntax-error",
    "module": "cfdc9520bbdd46b1f917e24ceb609cb5_2.java",
    "obj": "",
    "line": null,
    "column": null,
    "path": "cfdc9520bbdd46b1f917e24ceb609cb5_2.java",
    "symbol": "syntax-error",
    "message": "files/java/codes/good/MyTask2.java:24: error: class, interface, enum, or record expected\nexecutorService.execute(task1);\n^",
    "message-id": ""
  },
  {
    "type": "syntax-error",
    "module": "cfdc9520bbdd46b1f917e24ceb609cb5_2.java",
    "obj": "",
    "line": null,
    "column": null,
    "path": "cfdc9520bbdd46b1f917e24ceb609cb5_2.java",
    "symbol": "syntax-error",
    "message": "files/java/codes/good/MyTask2.java:25: error: class, interface, enum, or record expected\nexecutorService.execute(task2);\n^",
    "message-id": ""
  },
  {
    "type": "syntax-error",
    "module": "cfdc9520bbdd46b1f917e24ceb609cb5_2.java",
    "obj": "",
    "line": null,
    "column": null,
    "path": "cfdc9520bbdd46b1f917e24ceb609cb5_2.java",
    "symbol": "syntax-error",
    "message": "files/java/codes/good/MyTask2.java:26: error: class, interface, enum, or record expected\nexecutorService.execute(task3);\n^",
    "message-id": ""
  },
  {
    "type": "syntax-error",
    "module": "46b03d064ae1ee867e7710ba0889a4b5_0.java",
    "obj": "",
    "line": null,
    "column": null,
    "path": "46b03d064ae1ee867e7710ba0889a4b5_0.java",
    "symbol": "syntax-error",
    "message": "files/java/codes/good/Grid.java:1: error: '{' expected\npublic class Grid : MonoBehaviour {\n                 ^",
    "message-id": ""
  },
  {
    "type": "syntax-error",
    "module": "46b03d064ae1ee867e7710ba0889a4b5_0.java",
    "obj": "",
    "line": null,
    "column": null,
    "path": "46b03d064ae1ee867e7710ba0889a4b5_0.java",
    "symbol": "syntax-error",
    "message": "files/java/codes/good/Grid.java:5: error: ']' expected\n       private GameObject[,] grid;\n                          ^",
    "message-id": ""
  },
  {
    "type": "syntax-error",
    "module": "46b03d064ae1ee867e7710ba0889a4b5_0.java",
    "obj": "",
    "line": null,
    "column": null,
    "path": "46b03d064ae1ee867e7710ba0889a4b5_0.java",
    "symbol": "syntax-error",
    "message": "files/java/codes/good/Grid.java:5: error: <identifier> expected\n       private GameObject[,] grid;\n                           ^",
    "message-id": ""
  },
  {
    "type": "syntax-error",
    "module": "46b03d064ae1ee867e7710ba0889a4b5_0.java",
    "obj": "",
    "line": null,
    "column": null,
    "path": "46b03d064ae1ee867e7710ba0889a4b5_0.java",
    "symbol": "syntax-error",
    "message": "files/java/codes/good/Grid.java:5: error: <identifier> expected\n       private GameObject[,] grid;\n                                 ^",
    "message-id": ""
  },
  {
    "type": "syntax-error",
    "module": "499568487f6d00974cf6d08ff15e47da_2.java",
    "obj": "",
    "line": null,
    "column": null,
    "path": "499568487f6d00974cf6d08ff15e47da_2.java",
    "symbol": "syntax-error",
    "message": "files/java/codes/good/OrderViewModel.java:3: error: ';' expected\n    public int Id { get; set; }\n                 ^",
    "message-id": ""
  },
  {
    "type": "syntax-error",
    "module": "499568487f6d00974cf6d08ff15e47da_2.java",
    "obj": "",
    "line": null,
    "column": null,
    "path": "499568487f6d00974cf6d08ff15e47da_2.java",
    "symbol": "syntax-error",
    "message": "files/java/codes/good/OrderViewModel.java:3: error: not a statement\n    public int Id { get; set; }\n                    ^",
    "message-id": ""
  },
  {
    "type": "syntax-error",
    "module": "499568487f6d00974cf6d08ff15e47da_2.java",
    "obj": "",
    "line": null,
    "column": null,
    "path": "499568487f6d00974cf6d08ff15e47da_2.java",
    "symbol": "syntax-error",
    "message": "files/java/codes/good/OrderViewModel.java:3: error: not a statement\n    public int Id { get; set; }\n                         ^",
    "message-id": ""
  },
  {
    "type": "syntax-error",
    "module": "499568487f6d00974cf6d08ff15e47da_2.java",
    "obj": "",
    "line": null,
    "column": null,
    "path": "499568487f6d00974cf6d08ff15e47da_2.java",
    "symbol": "syntax-error",
    "message": "files/java/codes/good/OrderViewModel.java:4: error: ';' expected\n    public string CustomerName { get; set; }\n                              ^",
    "message-id": ""
  },
  {
    "type": "syntax-error",
    "module": "499568487f6d00974cf6d08ff15e47da_2.java",
    "obj": "",
    "line": null,
    "column": null,
    "path": "499568487f6d00974cf6d08ff15e47da_2.java",
    "symbol": "syntax-error",
    "message": "files/java/codes/good/OrderViewModel.java:4: error: not a statement\n    public string CustomerName { get; set; }\n                                 ^",
    "message-id": ""
  },
  {
    "type": "syntax-error",
    "module": "499568487f6d00974cf6d08ff15e47da_2.java",
    "obj": "",
    "line": null,
    "column": null,
    "path": "499568487f6d00974cf6d08ff15e47da_2.java",
    "symbol": "syntax-error",
    "message": "files/java/codes/good/OrderViewModel.java:4: error: not a statement\n    public string CustomerName { get; set; }\n                                      ^",
    "message-id": ""
  },
  {
    "type": "syntax-error",
    "module": "499568487f6d00974cf6d08ff15e47da_2.java",
    "obj": "",
    "line": null,
    "column": null,
    "path": "499568487f6d00974cf6d08ff15e47da_2.java",
    "symbol": "syntax-error",
    "message": "files/java/codes/good/OrderViewModel.java:5: error: ';' expected\n    public List<OrderDetailViewModel> OrderDetails { get; set; }\n                                                  ^",
    "message-id": ""
  },
  {
    "type": "syntax-error",
    "module": "499568487f6d00974cf6d08ff15e47da_2.java",
    "obj": "",
    "line": null,
    "column": null,
    "path": "499568487f6d00974cf6d08ff15e47da_2.java",
    "symbol": "syntax-error",
    "message": "files/java/codes/good/OrderViewModel.java:5: error: not a statement\n    public List<OrderDetailViewModel> OrderDetails { get; set; }\n                                                     ^",
    "message-id": ""
  },
  {
    "type": "syntax-error",
    "module": "499568487f6d00974cf6d08ff15e47da_2.java",
    "obj": "",
    "line": null,
    "column": null,
    "path": "499568487f6d00974cf6d08ff15e47da_2.java",
    "symbol": "syntax-error",
    "message": "files/java/codes/good/OrderViewModel.java:5: error: not a statement\n    public List<OrderDetailViewModel> OrderDetails { get; set; }\n                                                          ^",
    "message-id": ""
  },
  {
    "type": "syntax-error",
    "module": "499568487f6d00974cf6d08ff15e47da_2.java",
    "obj": "",
    "line": null,
    "column": null,
    "path": "499568487f6d00974cf6d08ff15e47da_2.java",
    "symbol": "syntax-error",
    "message": "files/java/codes/good/OrderViewModel.java:10: error: ';' expected\n    public int Id { get; set; }\n                 ^",
    "message-id": ""
  },
  {
    "type": "syntax-error",
    "module": "499568487f6d00974cf6d08ff15e47da_2.java",
    "obj": "",
    "line": null,
    "column": null,
    "path": "499568487f6d00974cf6d08ff15e47da_2.java",
    "symbol": "syntax-error",
    "message": "files/java/codes/good/OrderViewModel.java:10: error: not a statement\n    public int Id { get; set; }\n                    ^",
    "message-id": ""
  },
  {
    "type": "syntax-error",
    "module": "499568487f6d00974cf6d08ff15e47da_2.java",
    "obj": "",
    "line": null,
    "column": null,
    "path": "499568487f6d00974cf6d08ff15e47da_2.java",
    "symbol": "syntax-error",
    "message": "files/java/codes/good/OrderViewModel.java:10: error: not a statement\n    public int Id { get; set; }\n                         ^",
    "message-id": ""
  },
  {
    "type": "syntax-error",
    "module": "499568487f6d00974cf6d08ff15e47da_2.java",
    "obj": "",
    "line": null,
    "column": null,
    "path": "499568487f6d00974cf6d08ff15e47da_2.java",
    "symbol": "syntax-error",
    "message": "files/java/codes/good/OrderViewModel.java:11: error: ';' expected\n    public string ProductName { get; set; }\n                             ^",
    "message-id": ""
  },
  {
    "type": "syntax-error",
    "module": "499568487f6d00974cf6d08ff15e47da_2.java",
    "obj": "",
    "line": null,
    "column": null,
    "path": "499568487f6d00974cf6d08ff15e47da_2.java",
    "symbol": "syntax-error",
    "message": "files/java/codes/good/OrderViewModel.java:11: error: not a statement\n    public string ProductName { get; set; }\n                                ^",
    "message-id": ""
  },
  {
    "type": "syntax-error",
    "module": "499568487f6d00974cf6d08ff15e47da_2.java",
    "obj": "",
    "line": null,
    "column": null,
    "path": "499568487f6d00974cf6d08ff15e47da_2.java",
    "symbol": "syntax-error",
    "message": "files/java/codes/good/OrderViewModel.java:11: error: not a statement\n    public string ProductName { get; set; }\n                                     ^",
    "message-id": ""
  },
  {
    "type": "syntax-error",
    "module": "7e64ebaaddfefd7449ee3e5cc56e5ebf_9.java",
    "obj": "",
    "line": null,
    "column": null,
    "path": "7e64ebaaddfefd7449ee3e5cc56e5ebf_9.java",
    "symbol": "syntax-error",
    "message": "files/java/codes/good/UIManager.java:2: error: '{' expected\npublic class UIManager : MonoBehaviour\n                      ^",
    "message-id": ""
  },
  {
    "type": "syntax-error",
    "module": "7e64ebaaddfefd7449ee3e5cc56e5ebf_9.java",
    "obj": "",
    "line": null,
    "column": null,
    "path": "7e64ebaaddfefd7449ee3e5cc56e5ebf_9.java",
    "symbol": "syntax-error",
    "message": "files/java/codes/good/UIManager.java:5: error: ';' expected\n    public static UIManager Instance { get; private set; }\n                                    ^",
    "message-id": ""
  },
  {
    "type": "syntax-error",
    "module": "7e64ebaaddfefd7449ee3e5cc56e5ebf_9.java",
    "obj": "",
    "line": null,
    "column": null,
    "path": "7e64ebaaddfefd7449ee3e5cc56e5ebf_9.java",
    "symbol": "syntax-error",
    "message": "files/java/codes/good/UIManager.java:5: error: not a statement\n    public static UIManager Instance { get; private set; }\n                                       ^",
    "message-id": ""
  },
  {
    "type": "syntax-error",
    "module": "7e64ebaaddfefd7449ee3e5cc56e5ebf_9.java",
    "obj": "",
    "line": null,
    "column": null,
    "path": "7e64ebaaddfefd7449ee3e5cc56e5ebf_9.java",
    "symbol": "syntax-error",
    "message": "files/java/codes/good/UIManager.java:5: error: illegal start of expression\n    public static UIManager Instance { get; private set; }\n                                            ^",
    "message-id": ""
  },
  {
    "type": "syntax-error",
    "module": "7e64ebaaddfefd7449ee3e5cc56e5ebf_9.java",
    "obj": "",
    "line": null,
    "column": null,
    "path": "7e64ebaaddfefd7449ee3e5cc56e5ebf_9.java",
    "symbol": "syntax-error",
    "message": "files/java/codes/good/UIManager.java:5: error: <identifier> expected\n    public static UIManager Instance { get; private set; }\n                                                       ^",
    "message-id": ""
  },
  {
    "type": "syntax-error",
    "module": "7e64ebaaddfefd7449ee3e5cc56e5ebf_9.java",
    "obj": "",
    "line": null,
    "column": null,
    "path": "7e64ebaaddfefd7449ee3e5cc56e5ebf_9.java",
    "symbol": "syntax-error",
    "message": "files/java/codes/good/UIManager.java:7: error: class, interface, enum, or record expected\n    [SerializeField] private Image damageIndicator;\n    ^",
    "message-id": ""
  },
  {
    "type": "syntax-error",
    "module": "7e64ebaaddfefd7449ee3e5cc56e5ebf_9.java",
    "obj": "",
    "line": null,
    "column": null,
    "path": "7e64ebaaddfefd7449ee3e5cc56e5ebf_9.java",
    "symbol": "syntax-error",
    "message": "files/java/codes/good/UIManager.java:9: error: class, interface, enum, or record expected\n    private void Awake()\n            ^",
    "message-id": ""
  },
  {
    "type": "syntax-error",
    "module": "7e64ebaaddfefd7449ee3e5cc56e5ebf_9.java",
    "obj": "",
    "line": null,
    "column": null,
    "path": "7e64ebaaddfefd7449ee3e5cc56e5ebf_9.java",
    "symbol": "syntax-error",
    "message": "files/java/codes/good/UIManager.java:15: error: class, interface, enum, or record expected\n            DontDestroyOnLoad(gameObject);\n            ^",
    "message-id": ""
  },
  {
    "type": "syntax-error",
    "module": "7e64ebaaddfefd7449ee3e5cc56e5ebf_9.java",
    "obj": "",
    "line": null,
    "column": null,
    "path": "7e64ebaaddfefd7449ee3e5cc56e5ebf_9.java",
    "symbol": "syntax-error",
    "message": "files/java/codes/good/UIManager.java:16: error: class, interface, enum, or record expected\n        }\n        ^",
    "message-id": ""
  },
  {
    "type": "syntax-error",
    "module": "7e64ebaaddfefd7449ee3e5cc56e5ebf_9.java",
    "obj": "",
    "line": null,
    "column": null,
    "path": "7e64ebaaddfefd7449ee3e5cc56e5ebf_9.java",
    "symbol": "syntax-error",
    "message": "files/java/codes/good/UIManager.java:20: error: class, interface, enum, or record expected\n        }\n        ^",
    "message-id": ""
  },
  {
    "type": "syntax-error",
    "module": "7e64ebaaddfefd7449ee3e5cc56e5ebf_9.java",
    "obj": "",
    "line": null,
    "column": null,
    "path": "7e64ebaaddfefd7449ee3e5cc56e5ebf_9.java",
    "symbol": "syntax-error",
    "message": "files/java/codes/good/UIManager.java:23: error: class, interface, enum, or record expected\n    public void ShowDamageIndicator(Vector3 direction)\n           ^",
    "message-id": ""
  },
  {
    "type": "syntax-error",
    "module": "4c8071ac62cbfe9a2540dd139bfe8e24_4.java",
    "obj": "",
    "line": null,
    "column": null,
    "path": "4c8071ac62cbfe9a2540dd139bfe8e24_4.java",
    "symbol": "syntax-error",
    "message": "files/java/codes/good/ModItems.java:1: error: <identifier> expected\npackage your.package.name.init;\n             ^",
    "message-id": ""
  },
  {
    "type": "syntax-error",
    "module": "5743b07185ea97cd8d08ddba240e6f85_1.java",
    "obj": "",
    "line": null,
    "column": null,
    "path": "5743b07185ea97cd8d08ddba240e6f85_1.java",
    "symbol": "syntax-error",
    "message": "files/java/codes/good/PlaneControls.java:1: error: '{' expected\npublic class PlaneControls : MonoBehaviour\n                          ^",
    "message-id": ""
  },
  {
    "type": "syntax-error",
    "module": "5743b07185ea97cd8d08ddba240e6f85_1.java",
    "obj": "",
    "line": null,
    "column": null,
    "path": "5743b07185ea97cd8d08ddba240e6f85_1.java",
    "symbol": "syntax-error",
    "message": "files/java/codes/good/PlaneControls.java:4: error: ';' expected\n    public static float BOOST_RECHARGE_U { get; set; }\n                                        ^",
    "message-id": ""
  },
  {
    "type": "syntax-error",
    "module": "5743b07185ea97cd8d08ddba240e6f85_1.java",
    "obj": "",
    "line": null,
    "column": null,
    "path": "5743b07185ea97cd8d08ddba240e6f85_1.java",
    "symbol": "syntax-error",
    "message": "files/java/codes/good/PlaneControls.java:4: error: not a statement\n    public static float BOOST_RECHARGE_U { get; set; }\n                                           ^",
    "message-id": ""
  },
  {
    "type": "syntax-error",
    "module": "5743b07185ea97cd8d08ddba240e6f85_1.java",
    "obj": "",
    "line": null,
    "column": null,
    "path": "5743b07185ea97cd8d08ddba240e6f85_1.java",
    "symbol": "syntax-error",
    "message": "files/java/codes/good/PlaneControls.java:4: error: not a statement\n    public static float BOOST_RECHARGE_U { get; set; }\n                                                ^",
    "message-id": ""
  },
  {
    "type": "syntax-error",
    "module": "d0918a1dff3c16dea395c0fe2c973275_1.java",
    "obj": "",
    "line": null,
    "column": null,
    "path": "d0918a1dff3c16dea395c0fe2c973275_1.java",
    "symbol": "syntax-error",
    "message": "files/java/codes/good/ViewModel.java:1: error: class, interface, enum, or record expected\npublic partial class MainWindow : Window\n       ^",
    "message-id": ""
  },
  {
    "type": "syntax-error",
    "module": "d0918a1dff3c16dea395c0fe2c973275_1.java",
    "obj": "",
    "line": null,
    "column": null,
    "path": "d0918a1dff3c16dea395c0fe2c973275_1.java",
    "symbol": "syntax-error",
    "message": "files/java/codes/good/ViewModel.java:1: error: '{' expected\npublic partial class MainWindow : Window\n                               ^",
    "message-id": ""
  },
  {
    "type": "syntax-error",
    "module": "d0918a1dff3c16dea395c0fe2c973275_1.java",
    "obj": "",
    "line": null,
    "column": null,
    "path": "d0918a1dff3c16dea395c0fe2c973275_1.java",
    "symbol": "syntax-error",
    "message": "files/java/codes/good/ViewModel.java:12: error: ';' expected\n    public string MyText { get; set; } = \"Hello World\";\n                        ^",
    "message-id": ""
  },
  {
    "type": "syntax-error",
    "module": "d0918a1dff3c16dea395c0fe2c973275_1.java",
    "obj": "",
    "line": null,
    "column": null,
    "path": "d0918a1dff3c16dea395c0fe2c973275_1.java",
    "symbol": "syntax-error",
    "message": "files/java/codes/good/ViewModel.java:12: error: not a statement\n    public string MyText { get; set; } = \"Hello World\";\n                           ^",
    "message-id": ""
  },
  {
    "type": "syntax-error",
    "module": "d0918a1dff3c16dea395c0fe2c973275_1.java",
    "obj": "",
    "line": null,
    "column": null,
    "path": "d0918a1dff3c16dea395c0fe2c973275_1.java",
    "symbol": "syntax-error",
    "message": "files/java/codes/good/ViewModel.java:12: error: not a statement\n    public string MyText { get; set; } = \"Hello World\";\n                                ^",
    "message-id": ""
  },
  {
    "type": "syntax-error",
    "module": "d0918a1dff3c16dea395c0fe2c973275_1.java",
    "obj": "",
    "line": null,
    "column": null,
    "path": "d0918a1dff3c16dea395c0fe2c973275_1.java",
    "symbol": "syntax-error",
    "message": "files/java/codes/good/ViewModel.java:12: error: illegal start of type\n    public string MyText { get; set; } = \"Hello World\";\n                                       ^",
    "message-id": ""
  },
  {
    "type": "syntax-error",
    "module": "6969e8609ea619b8f327a1438073d9bb_0.java",
    "obj": "",
    "line": null,
    "column": null,
    "path": "6969e8609ea619b8f327a1438073d9bb_0.java",
    "symbol": "syntax-error",
    "message": "files/java/codes/good/SwipeControls.java:1: error: '{' expected\npublic class SwipeControls : MonoBehaviour\n                          ^",
    "message-id": ""
  },
  {
    "type": "syntax-error",
    "module": "6969e8609ea619b8f327a1438073d9bb_0.java",
    "obj": "",
    "line": null,
    "column": null,
    "path": "6969e8609ea619b8f327a1438073d9bb_0.java",
    "symbol": "syntax-error",
    "message": "files/java/codes/good/SwipeControls.java:3: error: illegal start of type\n    ...\n    ^",
    "message-id": ""
  },
  {
    "type": "syntax-error",
    "module": "1ac1f353c278202dd9b02986952bae0b_5.java",
    "obj": "",
    "line": null,
    "column": null,
    "path": "1ac1f353c278202dd9b02986952bae0b_5.java",
    "symbol": "syntax-error",
    "message": "files/java/codes/good/HPChangeBuffEffectHandler.java:1: error: '{' expected\npublic class HPChangeBuffEffectHandler : IBuffEffectHandler\n                                      ^",
    "message-id": ""
  },
  {
    "type": "syntax-error",
    "module": "1ac1f353c278202dd9b02986952bae0b_5.java",
    "obj": "",
    "line": null,
    "column": null,
    "path": "1ac1f353c278202dd9b02986952bae0b_5.java",
    "symbol": "syntax-error",
    "message": "files/java/codes/good/HPChangeBuffEffectHandler.java:9: error: '{' expected\npublic class AttackPowerChangeBuffEffectHandler : IBuffEffectHandler\n                                               ^",
    "message-id": ""
  },
  {
    "type": "syntax-error",
    "module": "9c51c592e7ab7b8dbe78d852dc449266_6.java",
    "obj": "",
    "line": null,
    "column": null,
    "path": "9c51c592e7ab7b8dbe78d852dc449266_6.java",
    "symbol": "syntax-error",
    "message": "files/java/codes/good/CustomAgent.java:1: error: '{' expected\npublic class CustomAgent : Agent\n                        ^",
    "message-id": ""
  },
  {
    "type": "syntax-error",
    "module": "9c51c592e7ab7b8dbe78d852dc449266_6.java",
    "obj": "",
    "line": null,
    "column": null,
    "path": "9c51c592e7ab7b8dbe78d852dc449266_6.java",
    "symbol": "syntax-error",
    "message": "files/java/codes/good/CustomAgent.java:6: error: <identifier> expected\n    public override void OnActionReceived(float[] vectorAction)\n                   ^",
    "message-id": ""
  },
  {
    "type": "syntax-error",
    "module": "dfc5c2ae982b06b316ef289682a21612_15.java",
    "obj": "",
    "line": null,
    "column": null,
    "path": "dfc5c2ae982b06b316ef289682a21612_15.java",
    "symbol": "syntax-error",
    "message": "files/java/codes/good/MyAgent.java:1: error: '{' expected\npublic class MyAgent : Agent\n                    ^",
    "message-id": ""
  },
  {
    "type": "syntax-error",
    "module": "32b6033f6d9994a3e02e5a609a2713be_5.java",
    "obj": "",
    "line": null,
    "column": null,
    "path": "32b6033f6d9994a3e02e5a609a2713be_5.java",
    "symbol": "syntax-error",
    "message": "files/java/codes/good/TimeEntry.java:5: error: ';' expected\n    public int Minutes \n                      ^",
    "message-id": ""
  },
  {
    "type": "syntax-error",
    "module": "32b6033f6d9994a3e02e5a609a2713be_5.java",
    "obj": "",
    "line": null,
    "column": null,
    "path": "32b6033f6d9994a3e02e5a609a2713be_5.java",
    "symbol": "syntax-error",
    "message": "files/java/codes/good/TimeEntry.java:7: error: not a statement\n        get { return _minutes; } \n        ^",
    "message-id": ""
  },
  {
    "type": "syntax-error",
    "module": "32b6033f6d9994a3e02e5a609a2713be_5.java",
    "obj": "",
    "line": null,
    "column": null,
    "path": "32b6033f6d9994a3e02e5a609a2713be_5.java",
    "symbol": "syntax-error",
    "message": "files/java/codes/good/TimeEntry.java:7: error: ';' expected\n        get { return _minutes; } \n           ^",
    "message-id": ""
  },
  {
    "type": "syntax-error",
    "module": "32b6033f6d9994a3e02e5a609a2713be_5.java",
    "obj": "",
    "line": null,
    "column": null,
    "path": "32b6033f6d9994a3e02e5a609a2713be_5.java",
    "symbol": "syntax-error",
    "message": "files/java/codes/good/TimeEntry.java:8: error: not a statement\n        set { _minutes = value; } \n        ^",
    "message-id": ""
  },
  {
    "type": "syntax-error",
    "module": "32b6033f6d9994a3e02e5a609a2713be_5.java",
    "obj": "",
    "line": null,
    "column": null,
    "path": "32b6033f6d9994a3e02e5a609a2713be_5.java",
    "symbol": "syntax-error",
    "message": "files/java/codes/good/TimeEntry.java:8: error: ';' expected\n        set { _minutes = value; } \n           ^",
    "message-id": ""
  },
  {
    "type": "syntax-error",
    "module": "32b6033f6d9994a3e02e5a609a2713be_5.java",
    "obj": "",
    "line": null,
    "column": null,
    "path": "32b6033f6d9994a3e02e5a609a2713be_5.java",
    "symbol": "syntax-error",
    "message": "files/java/codes/good/TimeEntry.java:11: error: ';' expected\n    public double Hours \n                       ^",
    "message-id": ""
  },
  {
    "type": "syntax-error",
    "module": "32b6033f6d9994a3e02e5a609a2713be_5.java",
    "obj": "",
    "line": null,
    "column": null,
    "path": "32b6033f6d9994a3e02e5a609a2713be_5.java",
    "symbol": "syntax-error",
    "message": "files/java/codes/good/TimeEntry.java:13: error: not a statement\n        get { return _minutes / 60.0; } \n        ^",
    "message-id": ""
  },
  {
    "type": "syntax-error",
    "module": "32b6033f6d9994a3e02e5a609a2713be_5.java",
    "obj": "",
    "line": null,
    "column": null,
    "path": "32b6033f6d9994a3e02e5a609a2713be_5.java",
    "symbol": "syntax-error",
    "message": "files/java/codes/good/TimeEntry.java:13: error: ';' expected\n        get { return _minutes / 60.0; } \n           ^",
    "message-id": ""
  },
  {
    "type": "syntax-error",
    "module": "32b6033f6d9994a3e02e5a609a2713be_5.java",
    "obj": "",
    "line": null,
    "column": null,
    "path": "32b6033f6d9994a3e02e5a609a2713be_5.java",
    "symbol": "syntax-error",
    "message": "files/java/codes/good/TimeEntry.java:14: error: not a statement\n        set { _minutes = (int)(value * 60); } \n        ^",
    "message-id": ""
  },
  {
    "type": "syntax-error",
    "module": "32b6033f6d9994a3e02e5a609a2713be_5.java",
    "obj": "",
    "line": null,
    "column": null,
    "path": "32b6033f6d9994a3e02e5a609a2713be_5.java",
    "symbol": "syntax-error",
    "message": "files/java/codes/good/TimeEntry.java:14: error: ';' expected\n        set { _minutes = (int)(value * 60); } \n           ^",
    "message-id": ""
  },
  {
    "type": "syntax-error",
    "module": "eb3ea3728d8fd0dad50aed266b77d23d_5.java",
    "obj": "",
    "line": null,
    "column": null,
    "path": "eb3ea3728d8fd0dad50aed266b77d23d_5.java",
    "symbol": "syntax-error",
    "message": "files/java/codes/good/CustomPair.java:19: error: class, interface, enum, or record expected\nList<CustomPair> processingTypeCodes = messages.stream()\n^",
    "message-id": ""
  },
  {
    "type": "syntax-error",
    "module": "3514637b7f2d32a086664d851b35ce9d_1.java",
    "obj": "",
    "line": null,
    "column": null,
    "path": "3514637b7f2d32a086664d851b35ce9d_1.java",
    "symbol": "syntax-error",
    "message": "files/java/codes/good/CollectibleCoin.java:1: error: class, interface, enum, or record expected\nusing UnityEngine;\n^",
    "message-id": ""
  },
  {
    "type": "syntax-error",
    "module": "3514637b7f2d32a086664d851b35ce9d_1.java",
    "obj": "",
    "line": null,
    "column": null,
    "path": "3514637b7f2d32a086664d851b35ce9d_1.java",
    "symbol": "syntax-error",
    "message": "files/java/codes/good/CollectibleCoin.java:3: error: '{' expected\npublic class CollectibleCoin : MonoBehaviour\n                            ^",
    "message-id": ""
  },
  {
    "type": "syntax-error",
    "module": "3514637b7f2d32a086664d851b35ce9d_1.java",
    "obj": "",
    "line": null,
    "column": null,
    "path": "3514637b7f2d32a086664d851b35ce9d_1.java",
    "symbol": "syntax-error",
    "message": "files/java/codes/good/CollectibleCoin.java:11: error: -> expected\n        animator = GetComponent<Animator>();\n                                           ^",
    "message-id": ""
  },
  {
    "type": "syntax-error",
    "module": "3514637b7f2d32a086664d851b35ce9d_1.java",
    "obj": "",
    "line": null,
    "column": null,
    "path": "3514637b7f2d32a086664d851b35ce9d_1.java",
    "symbol": "syntax-error",
    "message": "files/java/codes/good/CollectibleCoin.java:12: error: -> expected\n        particleSystem = GetComponentInChildren<ParticleSystem>();\n                                                                 ^",
    "message-id": ""
  },
  {
    "type": "syntax-error",
    "module": "3514637b7f2d32a086664d851b35ce9d_1.java",
    "obj": "",
    "line": null,
    "column": null,
    "path": "3514637b7f2d32a086664d851b35ce9d_1.java",
    "symbol": "syntax-error",
    "message": "files/java/codes/good/CollectibleCoin.java:33: error: not a statement\n            GetComponent<SpriteRenderer>().enabled = false;\n                        ^",
    "message-id": ""
  },
  {
    "type": "syntax-error",
    "module": "3514637b7f2d32a086664d851b35ce9d_1.java",
    "obj": "",
    "line": null,
    "column": null,
    "path": "3514637b7f2d32a086664d851b35ce9d_1.java",
    "symbol": "syntax-error",
    "message": "files/java/codes/good/CollectibleCoin.java:33: error: ';' expected\n            GetComponent<SpriteRenderer>().enabled = false;\n                                        ^",
    "message-id": ""
  },
  {
    "type": "syntax-error",
    "module": "3514637b7f2d32a086664d851b35ce9d_1.java",
    "obj": "",
    "line": null,
    "column": null,
    "path": "3514637b7f2d32a086664d851b35ce9d_1.java",
    "symbol": "syntax-error",
    "message": "files/java/codes/good/CollectibleCoin.java:36: error: not a statement\n            GetComponent<Collider2D>().enabled = false;\n                        ^",
    "message-id": ""
  },
  {
    "type": "syntax-error",
    "module": "3514637b7f2d32a086664d851b35ce9d_1.java",
    "obj": "",
    "line": null,
    "column": null,
    "path": "3514637b7f2d32a086664d851b35ce9d_1.java",
    "symbol": "syntax-error",
    "message": "files/java/codes/good/CollectibleCoin.java:36: error: ';' expected\n            GetComponent<Collider2D>().enabled = false;\n                                    ^",
    "message-id": ""
  },
  {
    "type": "syntax-error",
    "module": "e550792fb2adfa06cb6d576c12bf4612_1.java",
    "obj": "",
    "line": null,
    "column": null,
    "path": "e550792fb2adfa06cb6d576c12bf4612_1.java",
    "symbol": "syntax-error",
    "message": "files/java/codes/good/DraggableItem.java:2: error: class, interface, enum, or record expected\nusing UnityEngine;\n^",
    "message-id": ""
  },
  {
    "type": "syntax-error",
    "module": "e550792fb2adfa06cb6d576c12bf4612_1.java",
    "obj": "",
    "line": null,
    "column": null,
    "path": "e550792fb2adfa06cb6d576c12bf4612_1.java",
    "symbol": "syntax-error",
    "message": "files/java/codes/good/DraggableItem.java:3: error: class, interface, enum, or record expected\nusing UnityEngine.EventSystems;\n^",
    "message-id": ""
  },
  {
    "type": "syntax-error",
    "module": "e550792fb2adfa06cb6d576c12bf4612_1.java",
    "obj": "",
    "line": null,
    "column": null,
    "path": "e550792fb2adfa06cb6d576c12bf4612_1.java",
    "symbol": "syntax-error",
    "message": "files/java/codes/good/DraggableItem.java:4: error: class, interface, enum, or record expected\nusing UnityEngine.UI;\n^",
    "message-id": ""
  },
  {
    "type": "syntax-error",
    "module": "e550792fb2adfa06cb6d576c12bf4612_1.java",
    "obj": "",
    "line": null,
    "column": null,
    "path": "e550792fb2adfa06cb6d576c12bf4612_1.java",
    "symbol": "syntax-error",
    "message": "files/java/codes/good/DraggableItem.java:6: error: '{' expected\npublic class DraggableItem : MonoBehaviour, IBeginDragHandler, IDragHandler, IEndDragHandler {\n                          ^",
    "message-id": ""
  },
  {
    "type": "syntax-error",
    "module": "e550792fb2adfa06cb6d576c12bf4612_1.java",
    "obj": "",
    "line": null,
    "column": null,
    "path": "e550792fb2adfa06cb6d576c12bf4612_1.java",
    "symbol": "syntax-error",
    "message": "files/java/codes/good/DraggableItem.java:12: error: -> expected\n        canvas = GetComponentInParent<Canvas>();\n                                               ^",
    "message-id": ""
  },
  {
    "type": "syntax-error",
    "module": "e550792fb2adfa06cb6d576c12bf4612_1.java",
    "obj": "",
    "line": null,
    "column": null,
    "path": "e550792fb2adfa06cb6d576c12bf4612_1.java",
    "symbol": "syntax-error",
    "message": "files/java/codes/good/DraggableItem.java:13: error: -> expected\n        rectTransform = GetComponent<RectTransform>();\n                                                     ^",
    "message-id": ""
  },
  {
    "type": "syntax-error",
    "module": "e550792fb2adfa06cb6d576c12bf4612_1.java",
    "obj": "",
    "line": null,
    "column": null,
    "path": "e550792fb2adfa06cb6d576c12bf4612_1.java",
    "symbol": "syntax-error",
    "message": "files/java/codes/good/DraggableItem.java:14: error: -> expected\n        canvasGroup = GetComponent<CanvasGroup>();\n                                                 ^",
    "message-id": ""
  },
  {
    "type": "syntax-error",
    "module": "6150c403cdfd0b2c6789728bceacf3c0_0.java",
    "obj": "",
    "line": null,
    "column": null,
    "path": "6150c403cdfd0b2c6789728bceacf3c0_0.java",
    "symbol": "syntax-error",
    "message": "files/java/codes/good/GridManager.java:1: error: '{' expected\npublic class GridManager : MonoBehaviour {\n                        ^",
    "message-id": ""
  },
  {
    "type": "syntax-error",
    "module": "30ce0ca6e3dc0685d3858e7fbc23b37b_2.java",
    "obj": "",
    "line": null,
    "column": null,
    "path": "30ce0ca6e3dc0685d3858e7fbc23b37b_2.java",
    "symbol": "syntax-error",
    "message": "files/java/codes/good/Assignment.java:3: error: ';' expected\n    public int AssignmentID { get; set; }\n                           ^",
    "message-id": ""
  },
  {
    "type": "syntax-error",
    "module": "30ce0ca6e3dc0685d3858e7fbc23b37b_2.java",
    "obj": "",
    "line": null,
    "column": null,
    "path": "30ce0ca6e3dc0685d3858e7fbc23b37b_2.java",
    "symbol": "syntax-error",
    "message": "files/java/codes/good/Assignment.java:3: error: not a statement\n    public int AssignmentID { get; set; }\n                              ^",
    "message-id": ""
  },
  {
    "type": "syntax-error",
    "module": "30ce0ca6e3dc0685d3858e7fbc23b37b_2.java",
    "obj": "",
    "line": null,
    "column": null,
    "path": "30ce0ca6e3dc0685d3858e7fbc23b37b_2.java",
    "symbol": "syntax-error",
    "message": "files/java/codes/good/Assignment.java:3: error: not a statement\n    public int AssignmentID { get; set; }\n                                   ^\n100 errors\nonly showing the first 100 errors, of 1346 total; use -Xmaxerrs if you would like to see more",
    "message-id": ""
  }
]